pdftotextsimple/__init__.py
pdftotextsimple/function.py
pdftotextsimple-0.0.3.dist-info/LICENSE
pdftotextsimple-0.0.3.dist-info/METADATA
pdftotextsimple-0.0.3.dist-info/WHEEL
pdftotextsimple-0.0.3.dist-info/top_level.txt
pdftotextsimple-0.0.3.dist-info/RECORD
